ecommerce/__init__.py
ecommerce/ecommerce_api.py
ecommerce/services/__init__.py
ecommerce/services/ecommerce.py
netpay-ecommerce/__init__.py
netpay-ecommerce/ecommerce_api.py
netpay-ecommerce/services/__init__.py
netpay-ecommerce/services/ecommerce.py
netpay_ecommerce/__init__.py
netpay_ecommerce/client.py
netpay_ecommerce/ecommerce_api.py
netpay_ecommerce/resources.py
netpay_ecommerce/services/__init__.py
netpay_ecommerce/services/ecommerce.py
tests/__init__.py
tests/test_api.py
netpay_ecommerce_python-0.1.dist-info/LICENSE.txt
netpay_ecommerce_python-0.1.dist-info/METADATA
netpay_ecommerce_python-0.1.dist-info/WHEEL
netpay_ecommerce_python-0.1.dist-info/top_level.txt
netpay_ecommerce_python-0.1.dist-info/RECORD
