Metadata-Version: 2.1
Name: netpay-ecommerce-python
Version: 0.1
Summary: A Python scripts for consume eccomerce Api
Home-page: https://github.com/javatechy/dokr
Author: Netpay
Author-email: info@netpay.com.mx
License: UNKNOWN
Platform: UNKNOWN
Classifier: Programming Language :: Python :: 3
Classifier: License :: OSI Approved :: MIT License
Classifier: Operating System :: OS Independent
